wiker/__init__.py
wiker/__main__.py
wiker/main.py
wiker-0.0.1.dist-info/LICENSE
wiker-0.0.1.dist-info/METADATA
wiker-0.0.1.dist-info/WHEEL
wiker-0.0.1.dist-info/top_level.txt
wiker-0.0.1.dist-info/RECORD
