Metadata-Version: 2.1
Name: wiker
Version: 0.0.1
Summary: Library for wikipedia dataset collection
Home-page: https://github.com/anorprogrammer/wiker
Author: Shahobiddin Anorboyev
Author-email: anorprogrammer1127@gmail.com
License: MIT
Platform: UNKNOWN
Classifier: Development Status :: 1 - Planning
Classifier: Intended Audience :: Developers
Classifier: License :: OSI Approved :: MIT License
Classifier: Programming Language :: Python :: 3.7
Classifier: Programming Language :: Python :: 3.8
Classifier: Programming Language :: Python :: 3.9
Classifier: Programming Language :: Python :: 3.10
Classifier: Topic :: Software Development :: Libraries
Requires-Python: >=3.7
License-File: LICENSE
Requires-Dist: beautifulsoup4 (>=4.11)
Requires-Dist: requests (>=2.25)
